odoo/addons/pos_display_order_number/README.rst
odoo/addons/pos_display_order_number/__init__.py
odoo/addons/pos_display_order_number/__manifest__.py
odoo/addons/pos_display_order_number/i18n/fr.po
odoo/addons/pos_display_order_number/i18n/fr_CH.po
odoo/addons/pos_display_order_number/i18n/it.po
odoo/addons/pos_display_order_number/i18n/pos_display_order_number.pot
odoo/addons/pos_display_order_number/readme/CONTRIBUTORS.md
odoo/addons/pos_display_order_number/readme/CREDITS.md
odoo/addons/pos_display_order_number/readme/DESCRIPTION.md
odoo/addons/pos_display_order_number/static/description/icon.png
odoo/addons/pos_display_order_number/static/description/index.html
odoo/addons/pos_display_order_number/static/src/js/overrides/screens/order_summary/order_summary.esm.js
odoo/addons/pos_display_order_number/static/src/xml/pos_display_order_number.xml
odoo/addons/pos_display_order_number/static/tests/tours/DisplayOrderNumber.tour.esm.js
odoo/addons/pos_display_order_number/tests/__init__.py
odoo/addons/pos_display_order_number/tests/test_frontend.py
odoo_addon_pos_display_order_number-18.0.1.0.0.9.dist-info/METADATA
odoo_addon_pos_display_order_number-18.0.1.0.0.9.dist-info/WHEEL
odoo_addon_pos_display_order_number-18.0.1.0.0.9.dist-info/top_level.txt
odoo_addon_pos_display_order_number-18.0.1.0.0.9.dist-info/RECORD
